README.txt
setup.py
Products/__init__.py
Products.signalstack.egg-info/PKG-INFO
Products.signalstack.egg-info/SOURCES.txt
Products.signalstack.egg-info/dependency_links.txt
Products.signalstack.egg-info/namespace_packages.txt
Products.signalstack.egg-info/not-zip-safe
Products.signalstack.egg-info/requires.txt
Products.signalstack.egg-info/top_level.txt
Products/signalstack/__init__.py
Products/signalstack/configure.zcml
docs/HISTORY.txt