Metadata-Version: 1.0
Name: Products.signalstack
Version: 1.0rc1
Summary: Show stacktrace on signal
Home-page: UNKNOWN
Author: Jarn AS
Author-email: info@jarn.com
License: BSD
Platform: UNKNOWN
Classifier: Framework :: Zope2
Classifier: Intended Audience :: Developers
Classifier: License :: OSI Approved :: BSD License
Classifier: Programming Language :: Python
Classifier: Topic :: Software Development :: Libraries :: Python Modules
